mycalculatepackage/__init__.py
mycalcilatepackage-0.1.dist-info/LICENCE.txt
mycalcilatepackage-0.1.dist-info/METADATA
mycalcilatepackage-0.1.dist-info/WHEEL
mycalcilatepackage-0.1.dist-info/top_level.txt
mycalcilatepackage-0.1.dist-info/RECORD
