Metadata-Version: 2.1
Name: mycalcilatepackage
Version: 0.1
Summary: <Basic calculator>
Home-page: UNKNOWN
Author: Bhakthi poorna
Author-email: <bhakthipoorna@gmail.com>
License: UNKNOWN
Platform: UNKNOWN
Classifier: Programming Language :: Python :: 3
Classifier: License :: OSI Approved :: MIT License
Classifier: Operating System :: OS Independent
